README.md
pytecio.py
setup.py
pytecio.egg-info/PKG-INFO
pytecio.egg-info/SOURCES.txt
pytecio.egg-info/dependency_links.txt
pytecio.egg-info/top_level.txt