Metadata-Version: 1.1
Name: pytecio
Version: 0.2.0
Summary: tecio wrapper for python
Home-page: https://github.com/blacksong/pytecio
Author: blacksong
Author-email: blacksong@yeah.net
License: UNKNOWN
Platform: any
Classifier: Programming Language :: Python :: 3
Classifier: Operating System :: OS Independent
Classifier: Topic :: Software Development :: Libraries :: Python Modules
